pyflysight/__init__.py
pyflysight/cli.py
pyflysight/config_params.py
pyflysight/config_utils.py
pyflysight/exceptions.py
pyflysight/flysight_proc.py
pyflysight/flysight_utils.py
pyflysight/log_utils.py
pyflysight/py.typed
pyflysight/trim_app.py
pyflysight-0.9.2.dist-info/licenses/LICENSE
pyflysight-0.9.2.dist-info/WHEEL
pyflysight-0.9.2.dist-info/entry_points.txt
pyflysight-0.9.2.dist-info/METADATA
pyflysight-0.9.2.dist-info/RECORD
