Metadata-Version: 2.4
Name: pyflysight
Version: 0.9.2
Summary: Helper library for processing FlySight GPS flight logs.
Author: sco1
Author-email: sco1 <sco1.git@gmail.com>
License-Expression: MIT
License-File: LICENSE
Classifier: Development Status :: 4 - Beta
Classifier: Intended Audience :: Developers
Classifier: Operating System :: OS Independent
Classifier: Programming Language :: Python :: 3 :: Only
Classifier: Programming Language :: Python :: 3.11
Classifier: Programming Language :: Python :: 3.12
Classifier: Programming Language :: Python :: 3.13
Classifier: Programming Language :: Python :: 3.14
Classifier: Typing :: Typed
Requires-Dist: matplotlib-window~=1.0
Requires-Dist: polars[timezone]~=1.33
Requires-Dist: psutil~=7.0
Requires-Dist: sco1-misc~=0.1
Requires-Dist: typer-slim~=0.12
Requires-Python: >=3.11
Project-URL: Changelog, https://github.com/sco1/pyflysight/blob/main/CHANGELOG.md
Project-URL: Documentation, https://sco1.github.io/pyflysight/
Project-URL: Homepage, https://github.com/sco1/
Project-URL: Issues, https://github.com/sco1/pyflysight/issues
Project-URL: Repository, https://github.com/sco1/pyflysight.git
